CHANGES
LICENSE
MANIFEST.in
README
setup.py
wsgistraw.py
wsgistraw.egg-info/PKG-INFO
wsgistraw.egg-info/SOURCES.txt
wsgistraw.egg-info/dependency_links.txt
wsgistraw.egg-info/top_level.txt
