Metadata-Version: 1.0
Name: wsgistraw
Version: 0.1.2
Summary: Decorators for WSGI without start_response and write
Home-page: http://abstracthack.wordpress.com/wsgistraw
Author: Andrey Nordin
Author-email: UNKNOWN
License: GNU LGPL
Keywords: wsgi decorator start_response write
Platform: UNKNOWN
Classifier: Development Status :: 4 - Beta
Classifier: Environment :: Web Environment
Classifier: Intended Audience :: Developers
Classifier: License :: OSI Approved :: GNU Library or Lesser General Public License (LGPL)
Classifier: Operating System :: OS Independent
Classifier: Programming Language :: Python
Classifier: Topic :: Software Development :: Libraries
Classifier: Topic :: Internet :: WWW/HTTP :: WSGI
